LICENSE
README.md
setup.py
webtul/__init__.py
webtul/binancecli.py
webtul/crypto.py
webtul/dal.py
webtul/geo.py
webtul/img.py
webtul/jsonx.py
webtul/log.py
webtul/notice.py
webtul/path.py
webtul/rsa.py
webtul/storage.py
webtul/stringx.py
webtul/structx.py
webtul.egg-info/PKG-INFO
webtul.egg-info/SOURCES.txt
webtul.egg-info/dependency_links.txt
webtul.egg-info/requires.txt
webtul.egg-info/top_level.txt