Metadata-Version: 1.2
Name: webtul
Version: 1.7
Summary: A set of web/task developing tools.
Home-page: http://github.com/zagfai/webtul
Author: Zagfai
Author-email: zagfai@gmail.com
License: MIT License
Keywords: web,lib,library,toolkit
Platform: any
Requires-Python: >=3
